docksing.py
docksing-0.2.36.dist-info/licenses/LICENSE
docksing-0.2.36.dist-info/METADATA
docksing-0.2.36.dist-info/WHEEL
docksing-0.2.36.dist-info/entry_points.txt
docksing-0.2.36.dist-info/top_level.txt
docksing-0.2.36.dist-info/RECORD
