Metadata-Version: 2.4
Name: docksing
Version: 0.2.36
Summary: CLI Utility for deployment of containerized jobs on SLURM HPC 
Author: G. Angelotti
License-File: LICENSE
Requires-Dist: paramiko==3.4.0
Requires-Dist: scp==0.15.0
Requires-Dist: docker==7.1.0
Requires-Dist: tqdm==4.66.4
Dynamic: author
Dynamic: description
Dynamic: description-content-type
Dynamic: license-file
Dynamic: requires-dist
Dynamic: summary
